juju_query-0.0.1.dist-info/DESCRIPTION.rst
juju_query-0.0.1.dist-info/METADATA
juju_query-0.0.1.dist-info/RECORD
juju_query-0.0.1.dist-info/WHEEL
juju_query-0.0.1.dist-info/entry_points.txt
juju_query-0.0.1.dist-info/metadata.json
juju_query-0.0.1.dist-info/pbr.json
juju_query-0.0.1.dist-info/top_level.txt
jujuquery/__init__.py
jujuquery/info.py
jujuquery/search.py
