Metadata-Version: 2.0
Name: juju-query
Version: 0.0.1
Summary: Juju query charmstore
Home-page: https://github.com/battlemidget/juju-query
Author: Adam Stokes
Author-email: adam.stokes@ubuntu.com
License: UNKNOWN
Platform: UNKNOWN
Requires-Dist: theblues
